{
  "appleName": "Mouse Trap",
  "code": "🪤",
  "codepointsHex": [
    "U+1FAA4"
  ],
  "components": [
    {
      "appleName": "Mouse Trap",
      "code": "🪤",
      "codepointsHex": [
        "U+1FAA4"
      ],
      "currentCldrName": "Mouse Trap",
      "description": "<p>A trap used to catch a <a href=\"/mouse/\">mouse</a>, <a href=\"/rat/\">rat</a>, or other unwanted rodent.&nbsp;Metaphorically used in emoji form to suggest any kind of trap or entrapment.</p>\r\n\r\n<p>The style of trap shown on major platforms has a box held high with a single stick. A wedge of <a href=\"/cheese-wedge/\">cheese</a> is used to lure a mouse into the box, knocking the stick away and trapping &mdash; but not killing &mdash; the mouse.</p>\r\n\r\n<p>This is distinct from other traps which kill or injure upon capture.</p>",
      "id": "8171",
      "slug": "mouse-trap",
      "shortcodes": [
        {
          "code": ":mouse_trap:",
          "vendor": {
            "slug": "shortcodes",
            "title": "Emojipedia"
          }
        },
        {
          "code": ":mouse_trap:",
          "vendor": {
            "slug": "discord",
            "title": "Discord"
          }
        }
      ],
      "title": "Mouse Trap"
    }
  ],
  "currentCldrName": "Mouse Trap",
  "description": "<p>A trap used to catch a <a href=\"/mouse/\">mouse</a>, <a href=\"/rat/\">rat</a>, or other unwanted rodent.&nbsp;Metaphorically used in emoji form to suggest any kind of trap or entrapment.</p>\r\n\r\n<p>The style of trap shown on major platforms has a box held high with a single stick. A wedge of <a href=\"/cheese-wedge/\">cheese</a> is used to lure a mouse into the box, knocking the stick away and trapping &mdash; but not killing &mdash; the mouse.</p>\r\n\r\n<p>This is distinct from other traps which kill or injure upon capture.</p>",
  "emojiVersion": {
    "date": 1580256000,
    "name": "13.0",
    "slug": "emoji-13.0",
    "status": 0
  },
  "id": "8171",
  "shortcodes": [
    {
      "code": ":mouse_trap:",
      "vendor": {
        "slug": "shortcodes",
        "title": "Emojipedia"
      },
      "source": "cldr"
    },
    {
      "code": ":mouse_trap:",
      "vendor": {
        "slug": "discord",
        "title": "Discord"
      },
      "source": "discord"
    }
  ],
  "slug": "mouse-trap",
  "title": "Mouse Trap",
  "type": "SINGLE",
  "version": {
    "date": 1583798400,
    "description": "<p>Unicode 13.0 is the version of the Unicode Standard&nbsp;released on&nbsp;March 10, 2020. 55 new emoji&nbsp;code points were added in this release,&nbsp;with all 117 new emojis for 2020 (including sequences for gender and skin tone)&nbsp;listed under <a href=\"/emoji-13.0/\">Emoji 13.0</a>.</p>\r\n\r\n<ul>\r\n\t<li><a href=\"http://unicode.org/versions/Unicode13.0.0/\">🔣 Unicode 13.0.0 Specification</a></li>\r\n</ul>\r\n\r\n<p>More about <a href=\"https://blog.emojipedia.org/whats-new-in-unicode-13-0/\">what&#39;s new in Unicode 13.0</a>.</p>",
    "name": "13.0",
    "slug": "unicode-13.0",
    "status": 0
  },
  "fluentui_metadata": {
    "cldr": "mouse trap",
    "fromVersion": "13.0",
    "glyph": "🪤",
    "glyphAsUtfInEmoticons": [
      "mousetrap"
    ],
    "group": "Objects",
    "keywords": [
      "bait",
      "mouse trap",
      "mousetrap",
      "snare",
      "trap"
    ],
    "mappedToEmoticons": [
      "mousetrap"
    ],
    "tts": "mouse trap",
    "unicode": "1faa4"
  },
  "fluentui_folder": "mouse-trap"
}