{
  "alsoKnownAs": [
    "Blood Type AB"
  ],
  "appleName": "Blood Type AB",
  "code": "🆎",
  "codepointsHex": [
    "U+1F18E"
  ],
  "components": [
    {
      "alsoKnownAs": [
        "Blood Type AB"
      ],
      "appleName": "Blood Type AB",
      "code": "🆎",
      "codepointsHex": [
        "U+1F18E"
      ],
      "currentCldrName": "AB Button (Blood Type)",
      "description": "<p>A symbol representing Blood Type AB.&nbsp;Displayed as the letters AB on a red background.</p>",
      "id": "1227",
      "slug": "ab-button-blood-type",
      "shortcodes": [
        {
          "code": ":ab_button_blood_type_:",
          "vendor": {
            "slug": "shortcodes",
            "title": "Emojipedia"
          }
        },
        {
          "code": ":ab:",
          "vendor": {
            "slug": "github",
            "title": "GitHub"
          }
        },
        {
          "code": ":ab:",
          "vendor": {
            "slug": "slack",
            "title": "Slack"
          }
        },
        {
          "code": ":ab:",
          "vendor": {
            "slug": "discord",
            "title": "Discord"
          }
        }
      ],
      "title": "Negative Squared AB"
    }
  ],
  "currentCldrName": "AB Button (Blood Type)",
  "description": "<p>A symbol representing Blood Type AB.&nbsp;Displayed as the letters AB on a red background.</p>",
  "emojiVersion": {
    "date": 1438646400,
    "name": "1.0",
    "slug": "emoji-1.0",
    "status": 0
  },
  "id": "1227",
  "shortcodes": [
    {
      "code": ":ab_button_blood_type_:",
      "vendor": {
        "slug": "shortcodes",
        "title": "Emojipedia"
      },
      "source": "cldr"
    },
    {
      "code": ":ab:",
      "vendor": {
        "slug": "github",
        "title": "GitHub"
      },
      "source": "github"
    },
    {
      "code": ":ab:",
      "vendor": {
        "slug": "slack",
        "title": "Slack"
      },
      "source": "slack"
    },
    {
      "code": ":ab:",
      "vendor": {
        "slug": "discord",
        "title": "Discord"
      },
      "source": "discord"
    }
  ],
  "slug": "ab-button-blood-type",
  "title": "Negative Squared AB",
  "type": "SINGLE",
  "version": {
    "date": 1286755200,
    "description": "<p>Released in&nbsp;October&nbsp;2010, Unicode 6.0 was the first version of the Unicode Standard to support emoji.</p>\r\n\r\n<p>Some characters in <a href=\"/unicode-5.2/\">prior</a>&nbsp;versions of Unicode were retroactively updated to provide&nbsp;an emoji presentation. This release was the first to introduce new characters for the sole purpose of compatability with emojis being used in Japan.</p>",
    "name": "6.0",
    "slug": "unicode-6.0",
    "status": 0
  },
  "emoji_net_data": {
    "category": "Enclosed Alphanumeric Supplement -> White on black squared Latin letters",
    "keywords": [
      "blood type",
      "ab"
    ],
    "definition": "A symbol representing Blood Type AB. AB Button (blood Type) was approved as part of Unicode 6.0 in 2010 under the name “Negative Squared AB” http://emojipedia.org/negative-squared-ab/",
    "name": "AB button (blood type)",
    "unicode": "U+1F18E",
    "shortcode": ":ab:",
    "senses": {
      "adjectives": [],
      "verbs": [],
      "nouns": []
    }
  },
  "fluentui_metadata": {
    "cldr": "AB button (blood type)",
    "fromVersion": "0.6",
    "glyph": "🆎",
    "glyphAsUtfInEmoticons": [
      "1f18e_negativesquaredab"
    ],
    "group": "Symbols",
    "keywords": [
      "ab",
      "AB button (blood type)",
      "blood type"
    ],
    "mappedToEmoticons": [
      "1f18e_negativesquaredab"
    ],
    "tts": "AB button (blood type)",
    "unicode": "1f18e"
  },
  "fluentui_folder": "negative-squared-ab"
}