{
  "alsoKnownAs": [
    "Spew",
    "Throwing Up",
    "Vomit"
  ],
  "appleName": "Vomiting Face",
  "code": "🤮",
  "codepointsHex": [
    "U+1F92E"
  ],
  "components": [
    {
      "alsoKnownAs": [
        "Spew",
        "Throwing Up",
        "Vomit"
      ],
      "appleName": "Vomiting Face",
      "code": "🤮",
      "codepointsHex": [
        "U+1F92E"
      ],
      "currentCldrName": "Face Vomiting",
      "description": "<p>A yellow face with scrunched, X-shaped eyes spewing bright-green vomit. May represent physical illness or disgust, more intensely so than <a href=\"/nauseated-face/\">🤢 Nauseated Face</a>.</p>",
      "id": "2584",
      "slug": "face-vomiting",
      "shortcodes": [
        {
          "code": ":face_vomiting:",
          "vendor": {
            "slug": "shortcodes",
            "title": "Emojipedia"
          }
        },
        {
          "code": ":vomiting_face:",
          "vendor": {
            "slug": "github",
            "title": "GitHub"
          }
        },
        {
          "code": ":face_vomiting:",
          "vendor": {
            "slug": "slack",
            "title": "Slack"
          }
        },
        {
          "code": ":face_with_open_mouth_vomiting:",
          "vendor": {
            "slug": "slack",
            "title": "Slack"
          }
        },
        {
          "code": ":face_vomiting:",
          "vendor": {
            "slug": "discord",
            "title": "Discord"
          }
        }
      ],
      "title": "Face with Open Mouth Vomiting"
    }
  ],
  "currentCldrName": "Face Vomiting",
  "description": "<p>A yellow face with scrunched, X-shaped eyes spewing bright-green vomit. May represent physical illness or disgust, more intensely so than <a href=\"/nauseated-face/\">🤢 Nauseated Face</a>.</p>",
  "emojiVersion": {
    "date": 1495065600,
    "name": "5.0",
    "slug": "emoji-5.0",
    "status": 0
  },
  "id": "2584",
  "shortcodes": [
    {
      "code": ":face_vomiting:",
      "vendor": {
        "slug": "shortcodes",
        "title": "Emojipedia"
      },
      "source": "cldr"
    },
    {
      "code": ":vomiting_face:",
      "vendor": {
        "slug": "github",
        "title": "GitHub"
      },
      "source": "github"
    },
    {
      "code": ":face_vomiting:",
      "vendor": {
        "slug": "slack",
        "title": "Slack"
      },
      "source": "slack"
    },
    {
      "code": ":face_with_open_mouth_vomiting:",
      "vendor": {
        "slug": "slack",
        "title": "Slack"
      },
      "source": "slack"
    },
    {
      "code": ":face_vomiting:",
      "vendor": {
        "slug": "discord",
        "title": "Discord"
      },
      "source": "discord"
    }
  ],
  "slug": "face-vomiting",
  "title": "Face with Open Mouth Vomiting",
  "type": "SINGLE",
  "version": {
    "date": 1497916800,
    "description": "<p>Unicode 10.0 is the version of the Unicode Standard released on June 20, 2017.&nbsp;8,518 new characters were included with this update, of which&nbsp;56 were emoji characters.</p>\r\n\r\n<p>Only new emoji code points are listed on this page.&nbsp;For the full 2017 emoji list;&nbsp;see <a href=\"/emoji-5.0/\">Emoji 5.0</a>&nbsp;which included&nbsp;all 239 emoji additions including sequences for skin tone and gender.</p>\r\n\r\n<ul>\r\n\t<li><a href=\"/emoji-5.0/\">😃 Emoji 5.0 list</a></li>\r\n\t<li><a href=\"http://unicode.org/versions/Unicode10.0.0/\">🔣 Unicode 10.0.0 Specification</a></li>\r\n</ul>",
    "name": "10.0",
    "slug": "unicode-10.0",
    "status": 0
  },
  "fluentui_metadata": {
    "cldr": "face vomiting",
    "fromVersion": "5.0",
    "glyph": "🤮",
    "glyphAsUtfInEmoticons": [
      "puke"
    ],
    "group": "Smileys & Emotion",
    "keywords": [
      "face vomiting",
      "puke",
      "sick",
      "vomit"
    ],
    "mappedToEmoticons": [
      "puke"
    ],
    "tts": "face vomiting",
    "unicode": "1f92e"
  },
  "fluentui_folder": "face-with-open-mouth-vomiting"
}