{
  "alsoKnownAs": [
    "Blood Type O"
  ],
  "appleName": "Blood Type O",
  "code": "🅾️",
  "codepointsHex": [
    "U+1F17E",
    "U+FE0F"
  ],
  "components": [
    {
      "alsoKnownAs": [
        "Blood Type O"
      ],
      "appleName": "Blood Type O",
      "code": "🅾️",
      "codepointsHex": [
        "U+1F17E",
        "U+FE0F"
      ],
      "currentCldrName": "O Button (Blood Type)",
      "description": "<p>A symbol representing Blood Type O.&nbsp;Displayed as the letter O&nbsp;on a red background.</p>",
      "id": "1237",
      "slug": "o-button-blood-type",
      "shortcodes": [
        {
          "code": ":o_button_blood_type_:",
          "vendor": {
            "slug": "shortcodes",
            "title": "Emojipedia"
          }
        },
        {
          "code": ":o2:",
          "vendor": {
            "slug": "github",
            "title": "GitHub"
          }
        },
        {
          "code": ":o2:",
          "vendor": {
            "slug": "slack",
            "title": "Slack"
          }
        },
        {
          "code": ":o2:",
          "vendor": {
            "slug": "discord",
            "title": "Discord"
          }
        }
      ],
      "title": "Negative Squared Latin Capital Letter O"
    }
  ],
  "currentCldrName": "O Button (Blood Type)",
  "description": "<p>A symbol representing Blood Type O.&nbsp;Displayed as the letter O&nbsp;on a red background.</p>",
  "emojiVersion": {
    "date": 1438646400,
    "name": "1.0",
    "slug": "emoji-1.0",
    "status": 0
  },
  "id": "1237",
  "shortcodes": [
    {
      "code": ":o_button_blood_type_:",
      "vendor": {
        "slug": "shortcodes",
        "title": "Emojipedia"
      },
      "source": "cldr"
    },
    {
      "code": ":o2:",
      "vendor": {
        "slug": "github",
        "title": "GitHub"
      },
      "source": "github"
    },
    {
      "code": ":o2:",
      "vendor": {
        "slug": "slack",
        "title": "Slack"
      },
      "source": "slack"
    },
    {
      "code": ":o2:",
      "vendor": {
        "slug": "discord",
        "title": "Discord"
      },
      "source": "discord"
    }
  ],
  "slug": "o-button-blood-type",
  "title": "Negative Squared Latin Capital Letter O",
  "type": "SINGLE",
  "version": {
    "date": 1286755200,
    "description": "<p>Released in&nbsp;October&nbsp;2010, Unicode 6.0 was the first version of the Unicode Standard to support emoji.</p>\r\n\r\n<p>Some characters in <a href=\"/unicode-5.2/\">prior</a>&nbsp;versions of Unicode were retroactively updated to provide&nbsp;an emoji presentation. This release was the first to introduce new characters for the sole purpose of compatability with emojis being used in Japan.</p>",
    "name": "6.0",
    "slug": "unicode-6.0",
    "status": 0
  },
  "emoji_net_data": {
    "category": "Enclosed Alphanumeric Supplement -> White on black squared Latin letters",
    "keywords": [
      "blood type",
      "o"
    ],
    "definition": "A symbol representing Blood Type O. O Button (blood Type) was approved as part of Unicode 6.0 in 2010 under the name “Negative Squared Latin http://emojipedia.org/negative-squared-latin-capital-letter-o/",
    "name": "O button (blood type)",
    "unicode": "U+1F17E",
    "shortcode": ":o2:",
    "senses": {
      "adjectives": [],
      "verbs": [],
      "nouns": [
        {
          "bn:00019169n": [
            "A two-dimensional geometric figure, a disk, consisting of the set of all those points of a plane at a distance less than or equal to a fixed distance from another point.",
            "Three-dimensional geometric figure.",
            "Ellipse in which the two axes are of equal length; a plane curve generated by one point moving at a constant distance from a fixed point",
            "A circle is a simple shape of Euclidean geometry that is the set of all points in a plane that are at a given distance from a given point, the center.",
            "Circles are simple shapes of Euclidean geometry consisting of those points in a plane which are equidistant from a given point, the center.",
            "Simple shape of Euclidean geometry",
            "A two-dimensional, geometric shape that is made up of every point on a plane which is equidistant from the centre. May be drawn with a pair of compasses."
          ]
        }
      ]
    }
  },
  "fluentui_metadata": {
    "cldr": "O button (blood type)",
    "fromVersion": "0.6",
    "glyph": "🅾️",
    "group": "Symbols",
    "keywords": [
      "blood type",
      "o",
      "O button (blood type)"
    ],
    "mappedToEmoticons": [
      "1f17e_bloodtype0"
    ],
    "tts": "O button (blood type)",
    "unicode": "1f17e fe0f"
  },
  "fluentui_folder": "negative-squared-latin-capital-letter-o"
}